sepal/__init__.py
sepal/aifs.py
sepal/dce_fit.py
sepal/fitting.py
sepal/mt.py
sepal/pk_models.py
sepal/relaxivity.py
sepal/signal_models.py
sepal/t1_fit.py
sepal/t2star_fit.py
sepal/water_ex_models.py
sepal/utils/__init__.py
sepal/utils/imaging.py
sepal/utils/utilities.py
sepal-1.3.2.dist-info/LICENSE
sepal-1.3.2.dist-info/METADATA
sepal-1.3.2.dist-info/WHEEL
sepal-1.3.2.dist-info/top_level.txt
sepal-1.3.2.dist-info/RECORD
