Metadata-Version: 2.2
Name: sepal
Version: 1.3.2
Summary: Quantitative MRI processing
Author-email: Michael Thrippleton <mjt320@googlemail.com>
License:                                  Apache License
Project-URL: Homepage, https://github.com/mjt320/SEPAL
Keywords: MRI,perfusion,quantitative
Classifier: License :: OSI Approved :: Apache Software License
Classifier: Programming Language :: Python
Classifier: Programming Language :: Python :: 3
Requires-Python: >=3.7
License-File: LICENSE
Requires-Dist: numpy
Requires-Dist: scipy
Requires-Dist: nibabel
Requires-Dist: joblib
